Workbook

Sheet Cover
B2: SEEKING ALPHA ADVISORS
B3: Research, Advisory & Execution
B5: Alpha Legal — Platform Unit Economics
B6: Singapore VCC origination platform · 5-year model
B8: HOW TO USE
B9: 1. Set the two controls on the Assumptions tab: Scenario (Bull / Base / Bear) and Policy (conversion On / Off).
B10: 2. Edit any blue input cell (pricing, costs, scenario drivers) to flex the model.
B11: 3. The Model tab shows the active scenario in detail. Scenarios compares all three plus the policy convexity. Dashboard shows the headline KPIs and chart.
B12: 4. All figures recalculate live. Blue = input, black = formula.
B14: READ THIS
B15: Illustrative model built from public cost ranges, not a forecast. Unit prices and take rates are assumptions; willingness-to-pay is unproven.
B16: The conversion policy (onboarding SG companies / unit trusts to a VCC) is reported as under MAS consideration, not enacted. It is the upside lever, modelled via the Policy toggle.
... B19: a MERE conduit for the VISION · Wallahu a'lam

Sheet Assumptions
B2: ASSUMPTIONS & CONTROLS
B4: CONTROLS
B5: Scenario
B6: Base
B7: Policy: VCC conversion of SG cos / unit trusts
B8: On
B9: Policy flag (auto)
B10: =IF(B8="On",1,0) -> 1
B12: PRICING (S$)
B13: VCC document-set fee (per setup) | C13: 2000
B14: Sub-fund generation fee (per sub-fund) | C14: 500
B15: White-label licence (per firm, per year) | C15: 36000
B16: Recurring orchestration (per active VCC, per year) | C16: 600
B18: COSTS
B19: Fixed opex, Year 1 (dev, hosting, compliance, team) | C19: 450000
B20: Fixed opex growth (per year) | C20: 0.12
B21: Marginal cost per document set | C21: 100
B22: Marginal cost per sub-fund | C22: 30
B23: Active VCC retention (per year) | C23: 0.9
B25: SCENARIO DRIVERS
C26: Bull | D26: Base | E26: Bear | F26: Active
B27: Market new VCCs, Year 1 | C27: 350 | D27: 300 | E27: 250 | F27: =IF($B$6="Bull",C27,IF($B$6="Base",D27,E27)) -> 300
B28: Market growth (per year) | C28: 0.15 | D28: 0.1 | E28: 0.05 | F28: =IF($B$6="Bull",C28,IF($B$6="Base",D28,E28)) -> 0.1
B29: Platform share of new VCCs, Year 1 | C29: 0.05 | D29: 0.03 | E29: 0.02 | F29: =IF($B$6="Bull",C29,IF($B$6="Base",D29,E29)) -> 0.03
B30: Platform share of new VCCs, Year 5 | C30: 0.2 | D30: 0.12 | E30: 0.06 | F30: =IF($B$6="Bull",C30,IF($B$6="Base",D30,E30)) -> 0.12
B31: New sub-funds per active VCC, per year | C31: 0.8 | D31: 0.6 | E31: 0.4 | F31: =IF($B$6="Bull",C31,IF($B$6="Base",D31,E31)) -> 0.6
B32: White-label firms, Year 1 | C32: 5 | D32: 3 | E32: 2 | F32: =IF($B$6="Bull",C32,IF($B$6="Base",D32,E32)) -> 3
B33: White-label firms, Year 5 | C33: 30 | D33: 20 | E33: 10 | F33: =IF($B$6="Bull",C33,IF($B$6="Base",D33,E33)) -> 20
B34: Conversion-eligible base (SG cos / unit trusts) | C34: 12000 | D34: 10000 | E34: 8000 | F34: =IF($B$6="Bull",C34,IF($B$6="Base",D34,E34)) -> 10000
B35: Conversion adoption, per year (of remaining) | C35: 0.03 | D35: 0.02 | E35: 0.01 | F35: =IF($B$6="Bull",C35,IF($B$6="Base",D35,E35)) -> 0.02
B36: Platform share of conversions | C36: 0.12 | D36: 0.08 | E36: 0.04 | F36: =IF($B$6="Bull",C36,IF($B$6="Base",D36,E36)) -> 0.08

Sheet Model
B2: MODEL — ACTIVE SCENARIO
B3: =CONCATENATE("Scenario: ",Assumptions!B6," | Policy: ",Assumptions!B8) -> Scenario: Base | Policy: On
B5: 5-YEAR BUILD
C6: Year 1 | D6: Year 2 | E6: Year 3 | F6: Year 4 | G6: Year 5
B7: Market new VCCs | C7: =Assumptions!F$27 -> 300 | D7: =C7*(1+Assumptions!F$28) -> 330 | E7: =D7*(1+Assumptions!F$28) -> 363 | F7: =E7*(1+Assumptions!F$28) -> 399.3 | G7: =F7*(1+Assumptions!F$28) -> 439.23
B8: Platform share of new VCCs | C8: =Assumptions!F$29 -> 0.03 | D8: =Assumptions!F$29+(Assumptions!F$30-Assumptions!F$29)*1/4 -> 0.0525 | E8: =Assumptions!F$29+(Assumptions!F$30-Assumptions!F$29)*2/4 -> 0.075 | F8: =Assumptions!F$29+(Assumptions!F$30-Assumptions!F$29)*3/4 -> 0.0975 | G8: =Assumptions!F$30 -> 0.12
B9: Platform new VCCs (organic) | C9: =C7*C8 -> 9 | D9: =D7*D8 -> 17.325 | E9: =E7*E8 -> 27.225 | F9: =F7*F8 -> 38.93175 | G9: =G7*G8 -> 52.7076
B10: Conversion eligible (start) | C10: =Assumptions!F$34 -> 10000 | D10: =C10-C11 -> 9800 | E10: =D10-D11 -> 9604 | F10: =E10-E11 -> 9411.92 | G10: =F10-F11 -> 9223.6816
B11: Conversions (policy-gated) | C11: =C10*Assumptions!F$35*Assumptions!$B$10 -> 200 | D11: =D10*Assumptions!F$35*Assumptions!$B$10 -> 196 | E11: =E10*Assumptions!F$35*Assumptions!$B$10 -> 192.08 | F11: =F10*Assumptions!F$35*Assumptions!$B$10 -> 188.2384 | G11: =G10*Assumptions!F$35*Assumptions!$B$10 -> 184.47363
B12: Platform conversions | C12: =C11*Assumptions!F$36 -> 16 | D12: =D11*Assumptions!F$36 -> 15.68 | E12: =E11*Assumptions!F$36 -> 15.3664 | F12: =F11*Assumptions!F$36 -> 15.059072 | G12: =G11*Assumptions!F$36 -> 14.757891
B13: Platform new VCCs (total) | C13: =C9+C12 -> 25 | D13: =D9+D12 -> 33.005 | E13: =E9+E12 -> 42.5914 | F13: =F9+F12 -> 53.990822 | G13: =G9+G12 -> 67.465491
B14: Active platform VCCs | C14: =C13 -> 25 | D14: =C14*Assumptions!$C$23+D13 -> 55.505 | E14: =D14*Assumptions!$C$23+E13 -> 92.5459 | F14: =E14*Assumptions!$C$23+F13 -> 137.28213 | G14: =F14*Assumptions!$C$23+G13 -> 191.01941
B15: New sub-funds | C15: =C14*Assumptions!F$31 -> 15 | D15: =D14*Assumptions!F$31 -> 33.303 | E15: =E14*Assumptions!F$31 -> 55.52754 | F15: =F14*Assumptions!F$31 -> 82.369279 | G15: =G14*Assumptions!F$31 -> 114.61165
B16: White-label firms | C16: =Assumptions!F$32 -> 3 | D16: =Assumptions!F$32+(Assumptions!F$33-Assumptions!F$32)*1/4 -> 7.25 | E16: =Assumptions!F$32+(Assumptions!F$33-Assumptions!F$32)*2/4 -> 11.5 | F16: =Assumptions!F$32+(Assumptions!F$33-Assumptions!F$32)*3/4 -> 15.75 | G16: =Assumptions!F$33 -> 20
B17: VCC document-set revenue | C17: =C13*Assumptions!$C$13 -> 50000 | D17: =D13*Assumptions!$C$13 -> 66010 | E17: =E13*Assumptions!$C$13 -> 85182.8 | F17: =F13*Assumptions!$C$13 -> 107981.64 | G17: =G13*Assumptions!$C$13 -> 134930.98
B18: Sub-fund revenue | C18: =C15*Assumptions!$C$14 -> 7500 | D18: =D15*Assumptions!$C$14 -> 16651.5 | E18: =E15*Assumptions!$C$14 -> 27763.77 | F18: =F15*Assumptions!$C$14 -> 41184.64 | G18: =G15*Assumptions!$C$14 -> 57305.823
B19: White-label revenue | C19: =C16*Assumptions!$C$15 -> 108000 | D19: =D16*Assumptions!$C$15 -> 261000 | E19: =E16*Assumptions!$C$15 -> 414000 | F19: =F16*Assumptions!$C$15 -> 567000 | G19: =G16*Assumptions!$C$15 -> 720000
B20: Recurring orchestration revenue | C20: =C14*Assumptions!$C$16 -> 15000 | D20: =D14*Assumptions!$C$16 -> 33303 | E20: =E14*Assumptions!$C$16 -> 55527.54 | F20: =F14*Assumptions!$C$16 -> 82369.279 | G20: =G14*Assumptions!$C$16 -> 114611.65
B21: Total revenue | C21: =SUM(C17:C20) -> 180500 | D21: =SUM(D17:D20) -> 376964.5 | E21: =SUM(E17:E20) -> 582474.11 | F21: =SUM(F17:F20) -> 798535.56 | G21: =SUM(G17:G20) -> 1026848.4
B22: Marginal cost | C22: =C13*Assumptions!$C$21+C15*Assumptions!$C$22 -> 2950 | D22: =D13*Assumptions!$C$21+D15*Assumptions!$C$22 -> 4299.59 | E22: =E13*Assumptions!$C$21+E15*Assumptions!$C$22 -> 5924.9662 | F22: =F13*Assumptions!$C$21+F15*Assumptions!$C$22 -> 7870.1606 | G22: =G13*Assumptions!$C$21+G15*Assumptions!$C$22 -> 10184.898
B23: Contribution | C23: =C21-C22 -> 177550 | D23: =D21-D22 -> 372664.91 | E23: =E21-E22 -> 576549.14 | F23: =F21-F22 -> 790665.4 | G23: =G21-G22 -> 1016663.6
B24: Fixed opex | C24: =Assumptions!$C$19 -> 450000 | D24: =C24*(1+Assumptions!$C$20) -> 504000 | E24: =D24*(1+Assumptions!$C$20) -> 564480 | F24: =E24*(1+Assumptions!$C$20) -> 632217.6 | G24: =F24*(1+Assumptions!$C$20) -> 708083.71
B25: EBITDA | C25: =C23-C24 -> -272450 | D25: =D23-D24 -> -131335.09 | E25: =E23-E24 -> 12069.144 | F25: =F23-F24 -> 158447.8 | G25: =G23-G24 -> 308579.84
B26: EBITDA margin | C26: =IF(C21=0,0,C25/C21) -> -1.5094183 | D26: =IF(D21=0,0,D25/D21) -> -0.34840175 | E26: =IF(E21=0,0,E25/E21) -> 0.020720481 | F26: =IF(F21=0,0,F25/F21) -> 0.19842298 | G26: =IF(G21=0,0,G25/G21) -> 0.30051157
B28: Cumulative revenue | C28: =C21 -> 180500 | D28: =C28+D21 -> 557464.5 | E28: =D28+E21 -> 1139938.6 | F28: =E28+F21 -> 1938474.2 | G28: =F28+G21 -> 2965322.6
B29: Cumulative EBITDA | C29: =C25 -> -272450 | D29: =C29+D25 -> -403785.09 | E29: =D29+E25 -> -391715.95 | F29: =E29+F25 -> -233268.14 | G29: =F29+G25 -> 75311.695

Sheet Scenarios
B2: SCENARIO COMPARISON
B4: SCENARIO SUMMARY
C5: Bull | D5: Base | E5: Bear
B6: 5-year revenue | C6: =SUM(C34:G34) -> 5376549.2 | D6: =SUM(C58:G58) -> 2965322.6 | E6: =SUM(C82:G82) -> 1356278.9
B7: 5-year EBITDA | C7: =SUM(C38:G38) -> 2437138.2 | D7: =SUM(C62:G62) -> 75311.695 | E7: =SUM(C86:G86) -> -1511706.6
B8: Year 5 revenue | C8: =G34 -> 1851197.6 | D8: =G58 -> 1026848.4 | E8: =G82 -> 452233.23
B9: Year 5 EBITDA margin | C9: =G39 -> 0.60298805 | D9: =G63 -> 0.30051157 | E9: =G87 -> -0.57210622
B12: POLICY CONVEXITY — BASE CASE
C13: Policy Off | D13: Policy On | E13: Delta
B14: 5-year revenue | C14: =SUM(C130:G130) -> 2627583.5 | D14: =SUM(C106:G106) -> 2965322.6 | E14: =D14-C14 -> 337739.1
B15: 5-year EBITDA | C15: =SUM(C134:G134) -> -251060.82 | D15: =SUM(C110:G110) -> 75311.695 | E15: =D15-C15 -> 326372.51
B16: Revenue upside multiple (On / Off) | D16: =IF(C14=0,0,D14/C14) -> 1.128536
B18: Bull — calculation detail
C19: Year 1 | D19: Year 2 | E19: Year 3 | F19: Year 4 | G19: Year 5
B20: Market new VCCs | C20: =Assumptions!C$27 -> 350 | D20: =C20*(1+Assumptions!C$28) -> 402.5 | E20: =D20*(1+Assumptions!C$28) -> 462.875 | F20: =E20*(1+Assumptions!C$28) -> 532.30625 | G20: =F20*(1+Assumptions!C$28) -> 612.15219
B21: Platform share of new VCCs | C21: =Assumptions!C$29 -> 0.05 | D21: =Assumptions!C$29+(Assumptions!C$30-Assumptions!C$29)*1/4 -> 0.0875 | E21: =Assumptions!C$29+(Assumptions!C$30-Assumptions!C$29)*2/4 -> 0.125 | F21: =Assumptions!C$29+(Assumptions!C$30-Assumptions!C$29)*3/4 -> 0.1625 | G21: =Assumptions!C$30 -> 0.2
B22: Platform new VCCs (organic) | C22: =C20*C21 -> 17.5 | D22: =D20*D21 -> 35.21875 | E22: =E20*E21 -> 57.859375 | F22: =F20*F21 -> 86.499766 | G22: =G20*G21 -> 122.43044
B23: Conversion eligible (start) | C23: =Assumptions!C$34 -> 12000 | D23: =C23-C24 -> 11640 | E23: =D23-D24 -> 11290.8 | F23: =E23-E24 -> 10952.076 | G23: =F23-F24 -> 10623.514
B24: Conversions (policy-gated) | C24: =C23*Assumptions!C$35*Assumptions!$B$10 -> 360 | D24: =D23*Assumptions!C$35*Assumptions!$B$10 -> 349.2 | E24: =E23*Assumptions!C$35*Assumptions!$B$10 -> 338.724 | F24: =F23*Assumptions!C$35*Assumptions!$B$10 -> 328.56228 | G24: =G23*Assumptions!C$35*Assumptions!$B$10 -> 318.70541
B25: Platform conversions | C25: =C24*Assumptions!C$36 -> 43.2 | D25: =D24*Assumptions!C$36 -> 41.904 | E25: =E24*Assumptions!C$36 -> 40.64688 | F25: =F24*Assumptions!C$36 -> 39.427474 | G25: =G24*Assumptions!C$36 -> 38.244649
B26: Platform new VCCs (total) | C26: =C22+C25 -> 60.7 | D26: =D22+D25 -> 77.12275 | E26: =E22+E25 -> 98.506255 | F26: =F22+F25 -> 125.92724 | G26: =G22+G25 -> 160.67509
B27: Active platform VCCs | C27: =C26 -> 60.7 | D27: =C27*Assumptions!$C$23+D26 -> 131.75275 | E27: =D27*Assumptions!$C$23+E26 -> 217.08373 | F27: =E27*Assumptions!$C$23+F26 -> 321.3026 | G27: =F27*Assumptions!$C$23+G26 -> 449.84742
B28: New sub-funds | C28: =C27*Assumptions!C$31 -> 48.56 | D28: =D27*Assumptions!C$31 -> 105.4022 | E28: =E27*Assumptions!C$31 -> 173.66698 | F28: =F27*Assumptions!C$31 -> 257.04208 | G28: =G27*Assumptions!C$31 -> 359.87794
B29: White-label firms | C29: =Assumptions!C$32 -> 5 | D29: =Assumptions!C$32+(Assumptions!C$33-Assumptions!C$32)*1/4 -> 11.25 | E29: =Assumptions!C$32+(Assumptions!C$33-Assumptions!C$32)*2/4 -> 17.5 | F29: =Assumptions!C$32+(Assumptions!C$33-Assumptions!C$32)*3/4 -> 23.75 | G29: =Assumptions!C$33 -> 30
B30: VCC document-set revenue | C30: =C26*Assumptions!$C$13 -> 121400 | D30: =D26*Assumptions!$C$13 -> 154245.5 | E30: =E26*Assumptions!$C$13 -> 197012.51 | F30: =F26*Assumptions!$C$13 -> 251854.48 | G30: =G26*Assumptions!$C$13 -> 321350.17
B31: Sub-fund revenue | C31: =C28*Assumptions!$C$14 -> 24280 | D31: =D28*Assumptions!$C$14 -> 52701.1 | E31: =E28*Assumptions!$C$14 -> 86833.492 | F31: =F28*Assumptions!$C$14 -> 128521.04 | G31: =G28*Assumptions!$C$14 -> 179938.97
B32: White-label revenue | C32: =C29*Assumptions!$C$15 -> 180000 | D32: =D29*Assumptions!$C$15 -> 405000 | E32: =E29*Assumptions!$C$15 -> 630000 | F32: =F29*Assumptions!$C$15 -> 855000 | G32: =G29*Assumptions!$C$15 -> 1080000
B33: Recurring orchestration revenue | C33: =C27*Assumptions!$C$16 -> 36420 | D33: =D27*Assumptions!$C$16 -> 79051.65 | E33: =E27*Assumptions!$C$16 -> 130250.24 | F33: =F27*Assumptions!$C$16 -> 192781.56 | G33: =G27*Assumptions!$C$16 -> 269908.45
B34: Total revenue | C34: =SUM(C30:C33) -> 362100 | D34: =SUM(D30:D33) -> 690998.25 | E34: =SUM(E30:E33) -> 1044096.2 | F34: =SUM(F30:F33) -> 1428157.1 | G34: =SUM(G30:G33) -> 1851197.6
B35: Marginal cost | C35: =C26*Assumptions!$C$21+C28*Assumptions!$C$22 -> 7526.8 | D35: =D26*Assumptions!$C$21+D28*Assumptions!$C$22 -> 10874.341 | E35: =E26*Assumptions!$C$21+E28*Assumptions!$C$22 -> 15060.635 | F35: =F26*Assumptions!$C$21+F28*Assumptions!$C$22 -> 20303.986 | G35: =G26*Assumptions!$C$21+G28*Assumptions!$C$22 -> 26863.847
B36: Contribution | C36: =C34-C35 -> 354573.2 | D36: =D34-D35 -> 680123.91 | E36: =E34-E35 -> 1029035.6 | F36: =F34-F35 -> 1407853.1 | G36: =G34-G35 -> 1824333.8
B37: Fixed opex | C37: =Assumptions!$C$19 -> 450000 | D37: =C37*(1+Assumptions!$C$20) -> 504000 | E37: =D37*(1+Assumptions!$C$20) -> 564480 | F37: =E37*(1+Assumptions!$C$20) -> 632217.6 | G37: =F37*(1+Assumptions!$C$20) -> 708083.71
B38: EBITDA | C38: =C36-C37 -> -95426.8 | D38: =D36-D37 -> 176123.91 | E38: =E36-E37 -> 464555.6 | F38: =F36-F37 -> 775635.49 | G38: =G36-G37 -> 1116250
B39: EBITDA margin | C39: =IF(C34=0,0,C38/C34) -> -0.26353714 | D39: =IF(D34=0,0,D38/D34) -> 0.25488329 | E39: =IF(E34=0,0,E38/E34) -> 0.44493562 | F39: =IF(F34=0,0,F38/F34) -> 0.54310237 | G39: =IF(G34=0,0,G38/G34) -> 0.60298805
B42: Base — calculation detail
C43: Year 1 | D43: Year 2 | E43: Year 3 | F43: Year 4 | G43: Year 5
B44: Market new VCCs | C44: =Assumptions!D$27 -> 300 | D44: =C44*(1+Assumptions!D$28) -> 330 | E44: =D44*(1+Assumptions!D$28) -> 363 | F44: =E44*(1+Assumptions!D$28) -> 399.3 | G44: =F44*(1+Assumptions!D$28) -> 439.23
B45: Platform share of new VCCs | C45: =Assumptions!D$29 -> 0.03 | D45: =Assumptions!D$29+(Assumptions!D$30-Assumptions!D$29)*1/4 -> 0.0525 | E45: =Assumptions!D$29+(Assumptions!D$30-Assumptions!D$29)*2/4 -> 0.075 | F45: =Assumptions!D$29+(Assumptions!D$30-Assumptions!D$29)*3/4 -> 0.0975 | G45: =Assumptions!D$30 -> 0.12
B46: Platform new VCCs (organic) | C46: =C44*C45 -> 9 | D46: =D44*D45 -> 17.325 | E46: =E44*E45 -> 27.225 | F46: =F44*F45 -> 38.93175 | G46: =G44*G45 -> 52.7076
B47: Conversion eligible (start) | C47: =Assumptions!D$34 -> 10000 | D47: =C47-C48 -> 9800 | E47: =D47-D48 -> 9604 | F47: =E47-E48 -> 9411.92 | G47: =F47-F48 -> 9223.6816
B48: Conversions (policy-gated) | C48: =C47*Assumptions!D$35*Assumptions!$B$10 -> 200 | D48: =D47*Assumptions!D$35*Assumptions!$B$10 -> 196 | E48: =E47*Assumptions!D$35*Assumptions!$B$10 -> 192.08 | F48: =F47*Assumptions!D$35*Assumptions!$B$10 -> 188.2384 | G48: =G47*Assumptions!D$35*Assumptions!$B$10 -> 184.47363
B49: Platform conversions | C49: =C48*Assumptions!D$36 -> 16 | D49: =D48*Assumptions!D$36 -> 15.68 | E49: =E48*Assumptions!D$36 -> 15.3664 | F49: =F48*Assumptions!D$36 -> 15.059072 | G49: =G48*Assumptions!D$36 -> 14.757891
B50: Platform new VCCs (total) | C50: =C46+C49 -> 25 | D50: =D46+D49 -> 33.005 | E50: =E46+E49 -> 42.5914 | F50: =F46+F49 -> 53.990822 | G50: =G46+G49 -> 67.465491
B51: Active platform VCCs | C51: =C50 -> 25 | D51: =C51*Assumptions!$C$23+D50 -> 55.505 | E51: =D51*Assumptions!$C$23+E50 -> 92.5459 | F51: =E51*Assumptions!$C$23+F50 -> 137.28213 | G51: =F51*Assumptions!$C$23+G50 -> 191.01941
B52: New sub-funds | C52: =C51*Assumptions!D$31 -> 15 | D52: =D51*Assumptions!D$31 -> 33.303 | E52: =E51*Assumptions!D$31 -> 55.52754 | F52: =F51*Assumptions!D$31 -> 82.369279 | G52: =G51*Assumptions!D$31 -> 114.61165
B53: White-label firms | C53: =Assumptions!D$32 -> 3 | D53: =Assumptions!D$32+(Assumptions!D$33-Assumptions!D$32)*1/4 -> 7.25 | E53: =Assumptions!D$32+(Assumptions!D$33-Assumptions!D$32)*2/4 -> 11.5 | F53: =Assumptions!D$32+(Assumptions!D$33-Assumptions!D$32)*3/4 -> 15.75 | G53: =Assumptions!D$33 -> 20
B54: VCC document-set revenue | C54: =C50*Assumptions!$C$13 -> 50000 | D54: =D50*Assumptions!$C$13 -> 66010 | E54: =E50*Assumptions!$C$13 -> 85182.8 | F54: =F50*Assumptions!$C$13 -> 107981.64 | G54: =G50*Assumptions!$C$13 -> 134930.98
B55: Sub-fund revenue | C55: =C52*Assumptions!$C$14 -> 7500 | D55: =D52*Assumptions!$C$14 -> 16651.5 | E55: =E52*Assumptions!$C$14 -> 27763.77 | F55: =F52*Assumptions!$C$14 -> 41184.64 | G55: =G52*Assumptions!$C$14 -> 57305.823
B56: White-label revenue | C56: =C53*Assumptions!$C$15 -> 108000 | D56: =D53*Assumptions!$C$15 -> 261000 | E56: =E53*Assumptions!$C$15 -> 414000 | F56: =F53*Assumptions!$C$15 -> 567000 | G56: =G53*Assumptions!$C$15 -> 720000
B57: Recurring orchestration revenue | C57: =C51*Assumptions!$C$16 -> 15000 | D57: =D51*Assumptions!$C$16 -> 33303 | E57: =E51*Assumptions!$C$16 -> 55527.54 | F57: =F51*Assumptions!$C$16 -> 82369.279 | G57: =G51*Assumptions!$C$16 -> 114611.65
B58: Total revenue | C58: =SUM(C54:C57) -> 180500 | D58: =SUM(D54:D57) -> 376964.5 | E58: =SUM(E54:E57) -> 582474.11 | F58: =SUM(F54:F57) -> 798535.56 | G58: =SUM(G54:G57) -> 1026848.4
B59: Marginal cost | C59: =C50*Assumptions!$C$21+C52*Assumptions!$C$22 -> 2950 | D59: =D50*Assumptions!$C$21+D52*Assumptions!$C$22 -> 4299.59 | E59: =E50*Assumptions!$C$21+E52*Assumptions!$C$22 -> 5924.9662 | F59: =F50*Assumptions!$C$21+F52*Assumptions!$C$22 -> 7870.1606 | G59: =G50*Assumptions!$C$21+G52*Assumptions!$C$22 -> 10184.898
B60: Contribution | C60: =C58-C59 -> 177550 | D60: =D58-D59 -> 372664.91 | E60: =E58-E59 -> 576549.14 | F60: =F58-F59 -> 790665.4 | G60: =G58-G59 -> 1016663.6
B61: Fixed opex | C61: =Assumptions!$C$19 -> 450000 | D61: =C61*(1+Assumptions!$C$20) -> 504000 | E61: =D61*(1+Assumptions!$C$20) -> 564480 | F61: =E61*(1+Assumptions!$C$20) -> 632217.6 | G61: =F61*(1+Assumptions!$C$20) -> 708083.71
B62: EBITDA | C62: =C60-C61 -> -272450 | D62: =D60-D61 -> -131335.09 | E62: =E60-E61 -> 12069.144 | F62: =F60-F61 -> 158447.8 | G62: =G60-G61 -> 308579.84
B63: EBITDA margin | C63: =IF(C58=0,0,C62/C58) -> -1.5094183 | D63: =IF(D58=0,0,D62/D58) -> -0.34840175 | E63: =IF(E58=0,0,E62/E58) -> 0.020720481 | F63: =IF(F58=0,0,F62/F58) -> 0.19842298 | G63: =IF(G58=0,0,G62/G58) -> 0.30051157
B66: Bear — calculation detail
C67: Year 1 | D67: Year 2 | E67: Year 3 | F67: Year 4 | G67: Year 5
B68: Market new VCCs | C68: =Assumptions!E$27 -> 250 | D68: =C68*(1+Assumptions!E$28) -> 262.5 | E68: =D68*(1+Assumptions!E$28) -> 275.625 | F68: =E68*(1+Assumptions!E$28) -> 289.40625 | G68: =F68*(1+Assumptions!E$28) -> 303.87656
B69: Platform share of new VCCs | C69: =Assumptions!E$29 -> 0.02 | D69: =Assumptions!E$29+(Assumptions!E$30-Assumptions!E$29)*1/4 -> 0.03 | E69: =Assumptions!E$29+(Assumptions!E$30-Assumptions!E$29)*2/4 -> 0.04 | F69: =Assumptions!E$29+(Assumptions!E$30-Assumptions!E$29)*3/4 -> 0.05 | G69: =Assumptions!E$30 -> 0.06
B70: Platform new VCCs (organic) | C70: =C68*C69 -> 5 | D70: =D68*D69 -> 7.875 | E70: =E68*E69 -> 11.025 | F70: =F68*F69 -> 14.470313 | G70: =G68*G69 -> 18.232594
B71: Conversion eligible (start) | C71: =Assumptions!E$34 -> 8000 | D71: =C71-C72 -> 7920 | E71: =D71-D72 -> 7840.8 | F71: =E71-E72 -> 7762.392 | G71: =F71-F72 -> 7684.7681
B72: Conversions (policy-gated) | C72: =C71*Assumptions!E$35*Assumptions!$B$10 -> 80 | D72: =D71*Assumptions!E$35*Assumptions!$B$10 -> 79.2 | E72: =E71*Assumptions!E$35*Assumptions!$B$10 -> 78.408 | F72: =F71*Assumptions!E$35*Assumptions!$B$10 -> 77.62392 | G72: =G71*Assumptions!E$35*Assumptions!$B$10 -> 76.847681
B73: Platform conversions | C73: =C72*Assumptions!E$36 -> 3.2 | D73: =D72*Assumptions!E$36 -> 3.168 | E73: =E72*Assumptions!E$36 -> 3.13632 | F73: =F72*Assumptions!E$36 -> 3.1049568 | G73: =G72*Assumptions!E$36 -> 3.0739072
B74: Platform new VCCs (total) | C74: =C70+C73 -> 8.2 | D74: =D70+D73 -> 11.043 | E74: =E70+E73 -> 14.16132 | F74: =F70+F73 -> 17.575269 | G74: =G70+G73 -> 21.306501
B75: Active platform VCCs | C75: =C74 -> 8.2 | D75: =C75*Assumptions!$C$23+D74 -> 18.423 | E75: =D75*Assumptions!$C$23+E74 -> 30.74202 | F75: =E75*Assumptions!$C$23+F74 -> 45.243087 | G75: =F75*Assumptions!$C$23+G74 -> 62.02528
B76: New sub-funds | C76: =C75*Assumptions!E$31 -> 3.28 | D76: =D75*Assumptions!E$31 -> 7.3692 | E76: =E75*Assumptions!E$31 -> 12.296808 | F76: =F75*Assumptions!E$31 -> 18.097235 | G76: =G75*Assumptions!E$31 -> 24.810112
B77: White-label firms | C77: =Assumptions!E$32 -> 2 | D77: =Assumptions!E$32+(Assumptions!E$33-Assumptions!E$32)*1/4 -> 4 | E77: =Assumptions!E$32+(Assumptions!E$33-Assumptions!E$32)*2/4 -> 6 | F77: =Assumptions!E$32+(Assumptions!E$33-Assumptions!E$32)*3/4 -> 8 | G77: =Assumptions!E$33 -> 10
B78: VCC document-set revenue | C78: =C74*Assumptions!$C$13 -> 16400 | D78: =D74*Assumptions!$C$13 -> 22086 | E78: =E74*Assumptions!$C$13 -> 28322.64 | F78: =F74*Assumptions!$C$13 -> 35150.539 | G78: =G74*Assumptions!$C$13 -> 42613.002
B79: Sub-fund revenue | C79: =C76*Assumptions!$C$14 -> 1640 | D79: =D76*Assumptions!$C$14 -> 3684.6 | E79: =E76*Assumptions!$C$14 -> 6148.404 | F79: =F76*Assumptions!$C$14 -> 9048.6175 | G79: =G76*Assumptions!$C$14 -> 12405.056
B80: White-label revenue | C80: =C77*Assumptions!$C$15 -> 72000 | D80: =D77*Assumptions!$C$15 -> 144000 | E80: =E77*Assumptions!$C$15 -> 216000 | F80: =F77*Assumptions!$C$15 -> 288000 | G80: =G77*Assumptions!$C$15 -> 360000
B81: Recurring orchestration revenue | C81: =C75*Assumptions!$C$16 -> 4920 | D81: =D75*Assumptions!$C$16 -> 11053.8 | E81: =E75*Assumptions!$C$16 -> 18445.212 | F81: =F75*Assumptions!$C$16 -> 27145.852 | G81: =G75*Assumptions!$C$16 -> 37215.168
B82: Total revenue | C82: =SUM(C78:C81) -> 94960 | D82: =SUM(D78:D81) -> 180824.4 | E82: =SUM(E78:E81) -> 268916.26 | F82: =SUM(F78:F81) -> 359345.01 | G82: =SUM(G78:G81) -> 452233.23
B83: Marginal cost | C83: =C74*Assumptions!$C$21+C76*Assumptions!$C$22 -> 918.4 | D83: =D74*Assumptions!$C$21+D76*Assumptions!$C$22 -> 1325.376 | E83: =E74*Assumptions!$C$21+E76*Assumptions!$C$22 -> 1785.0362 | F83: =F74*Assumptions!$C$21+F76*Assumptions!$C$22 -> 2300.444 | G83: =G74*Assumptions!$C$21+G76*Assumptions!$C$22 -> 2874.9535
B84: Contribution | C84: =C82-C83 -> 94041.6 | D84: =D82-D83 -> 179499.02 | E84: =E82-E83 -> 267131.22 | F84: =F82-F83 -> 357044.56 | G84: =G82-G83 -> 449358.27
B85: Fixed opex | C85: =Assumptions!$C$19 -> 450000 | D85: =C85*(1+Assumptions!$C$20) -> 504000 | E85: =D85*(1+Assumptions!$C$20) -> 564480 | F85: =E85*(1+Assumptions!$C$20) -> 632217.6 | G85: =F85*(1+Assumptions!$C$20) -> 708083.71
B86: EBITDA | C86: =C84-C85 -> -355958.4 | D86: =D84-D85 -> -324500.98 | E86: =E84-E85 -> -297348.78 | F86: =F84-F85 -> -275173.04 | G86: =G84-G85 -> -258725.44
B87: EBITDA margin | C87: =IF(C82=0,0,C86/C82) -> -3.7485088 | D87: =IF(D82=0,0,D86/D82) -> -1.7945641 | E87: =IF(E82=0,0,E86/E82) -> -1.10573 | F87: =IF(F82=0,0,F86/F82) -> -0.76576279 | G87: =IF(G82=0,0,G86/G82) -> -0.57210622
B90: Base, Policy ON — calculation detail
C91: Year 1 | D91: Year 2 | E91: Year 3 | F91: Year 4 | G91: Year 5
B92: Market new VCCs | C92: =Assumptions!D$27 -> 300 | D92: =C92*(1+Assumptions!D$28) -> 330 | E92: =D92*(1+Assumptions!D$28) -> 363 | F92: =E92*(1+Assumptions!D$28) -> 399.3 | G92: =F92*(1+Assumptions!D$28) -> 439.23
B93: Platform share of new VCCs | C93: =Assumptions!D$29 -> 0.03 | D93: =Assumptions!D$29+(Assumptions!D$30-Assumptions!D$29)*1/4 -> 0.0525 | E93: =Assumptions!D$29+(Assumptions!D$30-Assumptions!D$29)*2/4 -> 0.075 | F93: =Assumptions!D$29+(Assumptions!D$30-Assumptions!D$29)*3/4 -> 0.0975 | G93: =Assumptions!D$30 -> 0.12
B94: Platform new VCCs (organic) | C94: =C92*C93 -> 9 | D94: =D92*D93 -> 17.325 | E94: =E92*E93 -> 27.225 | F94: =F92*F93 -> 38.93175 | G94: =G92*G93 -> 52.7076
B95: Conversion eligible (start) | C95: =Assumptions!D$34 -> 10000 | D95: =C95-C96 -> 9800 | E95: =D95-D96 -> 9604 | F95: =E95-E96 -> 9411.92 | G95: =F95-F96 -> 9223.6816
B96: Conversions (policy-gated) | C96: =C95*Assumptions!D$35*1 -> 200 | D96: =D95*Assumptions!D$35*1 -> 196 | E96: =E95*Assumptions!D$35*1 -> 192.08 | F96: =F95*Assumptions!D$35*1 -> 188.2384 | G96: =G95*Assumptions!D$35*1 -> 184.47363
B97: Platform conversions | C97: =C96*Assumptions!D$36 -> 16 | D97: =D96*Assumptions!D$36 -> 15.68 | E97: =E96*Assumptions!D$36 -> 15.3664 | F97: =F96*Assumptions!D$36 -> 15.059072 | G97: =G96*Assumptions!D$36 -> 14.757891
B98: Platform new VCCs (total) | C98: =C94+C97 -> 25 | D98: =D94+D97 -> 33.005 | E98: =E94+E97 -> 42.5914 | F98: =F94+F97 -> 53.990822 | G98: =G94+G97 -> 67.465491
B99: Active platform VCCs | C99: =C98 -> 25 | D99: =C99*Assumptions!$C$23+D98 -> 55.505 | E99: =D99*Assumptions!$C$23+E98 -> 92.5459 | F99: =E99*Assumptions!$C$23+F98 -> 137.28213 | G99: =F99*Assumptions!$C$23+G98 -> 191.01941
B100: New sub-funds | C100: =C99*Assumptions!D$31 -> 15 | D100: =D99*Assumptions!D$31 -> 33.303 | E100: =E99*Assumptions!D$31 -> 55.52754 | F100: =F99*Assumptions!D$31 -> 82.369279 | G100: =G99*Assumptions!D$31 -> 114.61165
B101: White-label firms | C101: =Assumptions!D$32 -> 3 | D101: =Assumptions!D$32+(Assumptions!D$33-Assumptions!D$32)*1/4 -> 7.25 | E101: =Assumptions!D$32+(Assumptions!D$33-Assumptions!D$32)*2/4 -> 11.5 | F101: =Assumptions!D$32+(Assumptions!D$33-Assumptions!D$32)*3/4 -> 15.75 | G101: =Assumptions!D$33 -> 20
B102: VCC document-set revenue | C102: =C98*Assumptions!$C$13 -> 50000 | D102: =D98*Assumptions!$C$13 -> 66010 | E102: =E98*Assumptions!$C$13 -> 85182.8 | F102: =F98*Assumptions!$C$13 -> 107981.64 | G102: =G98*Assumptions!$C$13 -> 134930.98
B103: Sub-fund revenue | C103: =C100*Assumptions!$C$14 -> 7500 | D103: =D100*Assumptions!$C$14 -> 16651.5 | E103: =E100*Assumptions!$C$14 -> 27763.77 | F103: =F100*Assumptions!$C$14 -> 41184.64 | G103: =G100*Assumptions!$C$14 -> 57305.823
B104: White-label revenue | C104: =C101*Assumptions!$C$15 -> 108000 | D104: =D101*Assumptions!$C$15 -> 261000 | E104: =E101*Assumptions!$C$15 -> 414000 | F104: =F101*Assumptions!$C$15 -> 567000 | G104: =G101*Assumptions!$C$15 -> 720000
B105: Recurring orchestration revenue | C105: =C99*Assumptions!$C$16 -> 15000 | D105: =D99*Assumptions!$C$16 -> 33303 | E105: =E99*Assumptions!$C$16 -> 55527.54 | F105: =F99*Assumptions!$C$16 -> 82369.279 | G105: =G99*Assumptions!$C$16 -> 114611.65
B106: Total revenue | C106: =SUM(C102:C105) -> 180500 | D106: =SUM(D102:D105) -> 376964.5 | E106: =SUM(E102:E105) -> 582474.11 | F106: =SUM(F102:F105) -> 798535.56 | G106: =SUM(G102:G105) -> 1026848.4
B107: Marginal cost | C107: =C98*Assumptions!$C$21+C100*Assumptions!$C$22 -> 2950 | D107: =D98*Assumptions!$C$21+D100*Assumptions!$C$22 -> 4299.59 | E107: =E98*Assumptions!$C$21+E100*Assumptions!$C$22 -> 5924.9662 | F107: =F98*Assumptions!$C$21+F100*Assumptions!$C$22 -> 7870.1606 | G107: =G98*Assumptions!$C$21+G100*Assumptions!$C$22 -> 10184.898
B108: Contribution | C108: =C106-C107 -> 177550 | D108: =D106-D107 -> 372664.91 | E108: =E106-E107 -> 576549.14 | F108: =F106-F107 -> 790665.4 | G108: =G106-G107 -> 1016663.6
B109: Fixed opex | C109: =Assumptions!$C$19 -> 450000 | D109: =C109*(1+Assumptions!$C$20) -> 504000 | E109: =D109*(1+Assumptions!$C$20) -> 564480 | F109: =E109*(1+Assumptions!$C$20) -> 632217.6 | G109: =F109*(1+Assumptions!$C$20) -> 708083.71
B110: EBITDA | C110: =C108-C109 -> -272450 | D110: =D108-D109 -> -131335.09 | E110: =E108-E109 -> 12069.144 | F110: =F108-F109 -> 158447.8 | G110: =G108-G109 -> 308579.84
B111: EBITDA margin | C111: =IF(C106=0,0,C110/C106) -> -1.5094183 | D111: =IF(D106=0,0,D110/D106) -> -0.34840175 | E111: =IF(E106=0,0,E110/E106) -> 0.020720481 | F111: =IF(F106=0,0,F110/F106) -> 0.19842298 | G111: =IF(G106=0,0,G110/G106) -> 0.30051157
...

Sheet Dashboard
B2: DASHBOARD
B3: =CONCATENATE("Active: ",Assumptions!B6," scenario, Policy ",Assumptions!B8) -> Active: Base scenario, Policy On
B5: HEADLINE (ACTIVE SCENARIO)
B6: 5-year revenue | C6: =SUM(Model!C21:G21) -> 2965322.6
B7: 5-year EBITDA | C7: =SUM(Model!C25:G25) -> 75311.695
B8: Year 5 revenue | C8: =Model!G21 -> 1026848.4
B9: Year 5 EBITDA | C9: =Model!G25 -> 308579.84
B10: Year 5 EBITDA margin | C10: =Model!G26 -> 0.30051157
B12: SCENARIO COMPARISON
C13: =Scenarios!C5 -> Bull | D13: =Scenarios!D5 -> Base | E13: =Scenarios!E5 -> Bear
B14: 5-year revenue | C14: =Scenarios!C6 -> 5376549.2 | D14: =Scenarios!D6 -> 2965322.6 | E14: =Scenarios!E6 -> 1356278.9
B15: 5-year EBITDA | C15: =Scenarios!C7 -> 2437138.2 | D15: =Scenarios!D7 -> 75311.695 | E15: =Scenarios!E7 -> -1511706.6
B16: Year 5 revenue | C16: =Scenarios!C8 -> 1851197.6 | D16: =Scenarios!D8 -> 1026848.4 | E16: =Scenarios!E8 -> 452233.23
C18: Year 1 | D18: Year 2 | E18: Year 3 | F18: Year 4 | G18: Year 5
B19: Revenue by year (chart data)
B20: Bull | C20: =Scenarios!C34 -> 362100 | D20: =Scenarios!D34 -> 690998.25 | E20: =Scenarios!E34 -> 1044096.2 | F20: =Scenarios!F34 -> 1428157.1 | G20: =Scenarios!G34 -> 1851197.6
B21: Base | C21: =Scenarios!C58 -> 180500 | D21: =Scenarios!D58 -> 376964.5 | E21: =Scenarios!E58 -> 582474.11 | F21: =Scenarios!F58 -> 798535.56 | G21: =Scenarios!G58 -> 1026848.4
B22: Bear | C22: =Scenarios!C82 -> 94960 | D22: =Scenarios!D82 -> 180824.4 | E22: =Scenarios!E82 -> 268916.26 | F22: =Scenarios!F82 -> 359345.01 | G22: =Scenarios!G82 -> 452233.23
